Logs/__init__.py
client/__init__.py
client/client.py
client/client_db.py
client/config_client_log.py
client/decorators.py
client/metaclasses.py
client/setup.py
server/__init__.py
server/config_server_log.py
server/decorators.py
server/metaclasses.py
server/server.py
server/server_db.py
server/setup.py
unit_tests/__init__.py
unit_tests/test_client.py
mess_server_gigacht-0.0.1.dist-info/LICENSE
mess_server_gigacht-0.0.1.dist-info/METADATA
mess_server_gigacht-0.0.1.dist-info/WHEEL
mess_server_gigacht-0.0.1.dist-info/top_level.txt
mess_server_gigacht-0.0.1.dist-info/RECORD
